simpel_pages/__init__.py
simpel_pages/apps.py
simpel_pages/forms.py
simpel_pages/helpers.py
simpel_pages/hooks.py
simpel_pages/managers.py
simpel_pages/middlewares.py
simpel_pages/routable.py
simpel_pages/search_indexes.py
simpel_pages/settings.py
simpel_pages/sitemaps.py
simpel_pages/urls.py
simpel_pages/utils.py
simpel_pages/version.py
simpel_pages/views.py
simpel_pages/admin/__init__.py
simpel_pages/admin/blocks.py
simpel_pages/admin/pages.py
simpel_pages/api/__init__.py
simpel_pages/api/serializers.py
simpel_pages/api/views.py
simpel_pages/api/viewsets.py
simpel_pages/locale/en/LC_MESSAGES/django.mo
simpel_pages/locale/en/LC_MESSAGES/django.po
simpel_pages/locale/id/LC_MESSAGES/django.mo
simpel_pages/locale/id/LC_MESSAGES/django.po
simpel_pages/management/__init__.py
simpel_pages/management/commands/__init__.py
simpel_pages/management/commands/init_demo_pages.py
simpel_pages/migrations/0001_initial.py
simpel_pages/migrations/0002_auto_20220402_0304.py
simpel_pages/migrations/0003_auto_20220402_1857.py
simpel_pages/migrations/0004_auto_20220403_2317.py
simpel_pages/migrations/0005_block_imageblock_richtextblock.py
simpel_pages/migrations/0006_auto_20220413_0624.py
simpel_pages/migrations/0007_auto_20220413_2206.py
simpel_pages/migrations/0008_auto_20220414_1649.py
simpel_pages/migrations/0009_htmlblock.py
simpel_pages/migrations/__init__.py
simpel_pages/models/__init__.py
simpel_pages/models/blocks.py
simpel_pages/models/pages.py
simpel_pages/static/.gitignore
simpel_pages/static/simpel_pages/css/main.bundle.css
simpel_pages/static/simpel_pages/css/plugins/.gitinclude
simpel_pages/static/simpel_pages/fonts/materialdesignicons-webfont.eot
simpel_pages/static/simpel_pages/fonts/materialdesignicons-webfont.ttf
simpel_pages/static/simpel_pages/fonts/materialdesignicons-webfont.woff
simpel_pages/static/simpel_pages/fonts/materialdesignicons-webfont.woff2
simpel_pages/static/simpel_pages/img/.gitinclude
simpel_pages/static/simpel_pages/js/main.js
simpel_pages-0.1.10.dist-info/LICENSE
simpel_pages-0.1.10.dist-info/METADATA
simpel_pages-0.1.10.dist-info/WHEEL
simpel_pages-0.1.10.dist-info/top_level.txt
simpel_pages-0.1.10.dist-info/RECORD
