Metadata-Version: 2.1
Name: simpel-pages
Version: 0.1.10
Summary: Enhanched Django FlatPages
Home-page: https://gitlab.com/sasriawesome/simpel_pages
Author: Rizki Sasri Dwitama
Author-email: sasri.works@gmail.com
License: MIT
Project-URL: Documentation, https://gitlab.com/sasriawesome/simpel_pages/-/wikis/
Project-URL: Source, https://gitlab.com/sasriawesome/simpel_pages
Platform: UNKNOWN
Classifier: Environment :: Web Environment
Classifier: Framework :: Django
Classifier: Intended Audience :: Developers
Classifier: License :: OSI Approved :: MIT License
Classifier: Operating System :: OS Independent
Classifier: Programming Language :: Python
Classifier: Programming Language :: Python :: 3
Classifier: Programming Language :: Python :: 3 :: Only
Classifier: Programming Language :: Python :: 3.8
Classifier: Programming Language :: Python :: 3.9
Classifier: Topic :: Internet :: WWW/HTTP
Classifier: Topic :: Internet :: WWW/HTTP :: Dynamic Content
Classifier: Topic :: Internet :: WWW/HTTP :: WSGI
Classifier: Topic :: Software Development :: Libraries :: Python Modules
Classifier: Topic :: Software Development :: Libraries :: Application Frameworks
Requires-Python: >=3.6
License-File: LICENSE
Requires-Dist: django (<4.0,>=3.2.8)
Requires-Dist: django-tinymce
Requires-Dist: django-filer
Requires-Dist: django-mptt
Requires-Dist: django-taggit
Requires-Dist: django-nested-admin
Requires-Dist: django-haystack
Requires-Dist: simpel-themes
Requires-Dist: simpel-settings
Requires-Dist: simpel-hookup
Requires-Dist: simpel-atomics
Requires-Dist: easy-thumbnails
Requires-Dist: whoosh
Requires-Dist: requests
